blobby/__init__.py
blobby/aws.py
blobby/azure.py
blobby/error.py
blobby/filesystem.py
blobby/gcp.py
blobby/memory.py
blobby/py.typed
blobby/storage.py
blobby-0.2.1.dist-info/LICENSE
blobby-0.2.1.dist-info/METADATA
blobby-0.2.1.dist-info/WHEEL
blobby-0.2.1.dist-info/RECORD
