Metadata-Version: 2.1
Name: blobby
Version: 0.2.1
Summary: Cloud provider agnostic library for object storage.
Home-page: https://github.com/davidsteiner/blobby
License: MIT
Author: David Steiner
Author-email: david_j_steiner@yahoo.co.nz
Requires-Python: >=3.10,<4.0
Classifier: Intended Audience :: Developers
Classifier: License :: OSI Approved :: MIT License
Classifier: Programming Language :: Python :: 3
Classifier: Programming Language :: Python :: 3.10
Classifier: Programming Language :: Python :: 3.11
Classifier: Programming Language :: Python :: 3.12
Classifier: Typing :: Typed
Provides-Extra: aws
Provides-Extra: azure
Provides-Extra: gcp
Requires-Dist: azure-storage-blob (>=12,<13) ; extra == "azure"
Requires-Dist: boto3 (>=1.34,<2.0) ; extra == "aws"
Requires-Dist: google-cloud-storage (>=2.17.0,<3.0.0) ; extra == "gcp"
Requires-Dist: pydantic (>=2,<3)
Project-URL: Repository, https://github.com/davidsteiner/blobby
